clipn/__init__.py
clipn/model.py
clipn-0.1.0.dist-info/LICENSE
clipn-0.1.0.dist-info/METADATA
clipn-0.1.0.dist-info/WHEEL
clipn-0.1.0.dist-info/top_level.txt
clipn-0.1.0.dist-info/RECORD
